decker/__init__.py
decker/__main__.py
decker/conf.py
decker/management.py
decker/utils.py
decker/contrib/__init__.py
decker/contrib/ramos.py
decker/format/__init__.py
decker/format/command.py
decker/format/pool.py
decker/format/services.py
decker/format/backends/__init__.py
decker/format/backends/autoflake.py
decker/format/backends/base.py
decker/format/backends/black.py
decker/format/backends/docformatter.py
decker/format/backends/isort.py
decker/format/backends/unify.py
decker-0.3.0.dist-info/LICENSE
decker-0.3.0.dist-info/METADATA
decker-0.3.0.dist-info/WHEEL
decker-0.3.0.dist-info/entry_points.txt
decker-0.3.0.dist-info/top_level.txt
decker-0.3.0.dist-info/RECORD
