Metadata-Version: 2.1
Name: decker
Version: 0.3.0
Summary: Simple development tool that simplifies a pythonist's daily tasks.
Home-page: https://github.com/douglasfarinelli/decker
Author: Douglas Farinelli
License: MIT
Platform: UNKNOWN
Classifier: Development Status :: 4 - Beta
Classifier: Environment :: Console
Classifier: License :: OSI Approved :: MIT License
Classifier: Programming Language :: Python :: 3
Classifier: Programming Language :: Python :: 3 :: Only
Classifier: Programming Language :: Python :: 3.6
Classifier: Programming Language :: Python :: 3.7
Classifier: Programming Language :: Python :: 3.8
Classifier: Programming Language :: Python :: 3.9
Requires-Python: >=3.6
Requires-Dist: autoflake
Requires-Dist: black (>=20.8b1)
Requires-Dist: click
Requires-Dist: colorama
Requires-Dist: docformatter
Requires-Dist: ipython
Requires-Dist: isort (>=5.6.4)
Requires-Dist: pdbpp
Requires-Dist: ramos
Requires-Dist: toml
Requires-Dist: unify
